django_agilesites/__init__.py
django_agilesites/loaders.py
django_agilesites/middleware.py
django_agilesites/models.py
django_agilesites/utils.py
django_agilesites/views.py
django_agilesites-1.1.0.dist-info/LICENSE.txt
django_agilesites-1.1.0.dist-info/METADATA
django_agilesites-1.1.0.dist-info/RECORD
django_agilesites-1.1.0.dist-info/WHEEL
django_agilesites-1.1.0.dist-info/top_level.txt
