Metadata-Version: 2.1
Name: django-agilesites
Version: 1.1.0
Summary: Dynamic switching of the settings.SIDE_ID for a Django Project
Home-page: https://github.com/pivotal-energy-solutions/django-agilesites
Author: Pivotal Energy Solutions
Author-email: sklass@pivotalenergysolutions.com
License: UNKNOWN
Download-URL: https://github.com/pivotal-energy-solutions/django-agilesites/archive/1.1.0.tar.gz
Project-URL: Source, https://github.com/pivotal-energy-solutions/django-agilesites
Project-URL: Bug Reports, https://github.com/pivotal-energy-solutions/django-agilesites/issues
Project-URL: Say Thanks!, http://saythanks.io/to/rh0dium
Keywords: django sites
Platform: UNKNOWN
Classifier: Development Status :: 5 - Production/Stable
Classifier: Environment :: Web Environment
Classifier: Framework :: Django
Classifier: License :: OSI Approved :: Apache Software License
Classifier: Programming Language :: Python :: 2
Classifier: Programming Language :: Python :: 2.7
Classifier: Topic :: Internet :: WWW/HTTP
Classifier: Topic :: Internet :: WWW/HTTP :: Dynamic Content
Classifier: Topic :: Software Development :: Libraries :: Python Modules
Requires-Dist: django (<2,>=1.9)
